johnpackagetest/__init__.py
johnpackagetest-0.1.2.dist-info/METADATA
johnpackagetest-0.1.2.dist-info/WHEEL
johnpackagetest-0.1.2.dist-info/top_level.txt
johnpackagetest-0.1.2.dist-info/RECORD
